{
  "id": "MAP_ROUTE9",
  "name": "Route9",
  "layout": "LAYOUT_ROUTE9",
  "music": "MUS_RG_ROUTE3",
  "region_map_section": "MAPSEC_ROUTE_9",
  "requires_flash": false,
  "weather": "WEATHER_NONE",
  "map_type": "MAP_TYPE_ROUTE",
  "allow_cycling": true,
  "allow_escaping": true,
  "allow_running": true,
  "show_map_name": true,
  "battle_scene": "MAP_BATTLE_SCENE_NORMAL",
  "connections": [
    {
      "map": "MAP_CERULEAN_CITY",
      "offset": -30,
      "direction": "left"
    },
    {
      "map": "MAP_ROUTE10",
      "offset": 64,
      "direction": "down"
    },
    {
      "map": "MAP_ROUTE25A",
      "offset": 50,
      "direction": "up"
    }
  ],
  "object_events": [
    {
      "graphics_id": "OBJ_EVENT_GFX_CAMPER",
      "x": 14,
      "y": 19,
      "elevation": 3,
      "movement_type": "MOVEMENT_TYPE_FACE_LEFT",
      "movement_range_x": 0,
      "movement_range_y": 0,
      "trainer_type": "TRAINER_TYPE_NONE",
      "trainer_sight_or_berry_tree_id": "0",
      "script": "FortreeCity_Mart_EventScript_Boy",
      "flag": "0"
    },
    {
      "graphics_id": "OBJ_EVENT_GFX_HIKER",
      "x": 19,
      "y": 28,
      "elevation": 0,
      "movement_type": "MOVEMENT_TYPE_FACE_UP",
      "movement_range_x": 0,
      "movement_range_y": 3,
      "trainer_type": "TRAINER_TYPE_NONE",
      "trainer_sight_or_berry_tree_id": "0",
      "script": "BattleFrontier_Lounge3_EventScript_Man",
      "flag": "0"
    },
    {
      "graphics_id": "OBJ_EVENT_GFX_BUG_CATCHER",
      "x": 41,
      "y": 9,
      "elevation": 3,
      "movement_type": "MOVEMENT_TYPE_WANDER_AROUND",
      "movement_range_x": 0,
      "movement_range_y": 1,
      "trainer_type": "TRAINER_TYPE_NONE",
      "trainer_sight_or_berry_tree_id": "0",
      "script": "RustboroCity_EventScript_Man2",
      "flag": "0"
    },
    {
      "graphics_id": "OBJ_EVENT_GFX_HIKER",
      "x": 50,
      "y": 17,
      "elevation": 0,
      "movement_type": "MOVEMENT_TYPE_FACE_RIGHT",
      "movement_range_x": 0,
      "movement_range_y": 3,
      "trainer_type": "TRAINER_TYPE_NONE",
      "trainer_sight_or_berry_tree_id": "0",
      "script": "BattleFrontier_Lounge3_EventScript_Man",
      "flag": "0"
    },
    {
      "graphics_id": "OBJ_EVENT_GFX_PICNICKER",
      "x": 71,
      "y": 17,
      "elevation": 3,
      "movement_type": "MOVEMENT_TYPE_WANDER_AROUND",
      "movement_range_x": 0,
      "movement_range_y": 0,
      "trainer_type": "TRAINER_TYPE_NONE",
      "trainer_sight_or_berry_tree_id": "0",
      "script": "FortreeCity_Mart_EventScript_Boy",
      "flag": "0"
    }
  ],
  "warp_events": [

  ],
  "coord_events": [

  ],
  "bg_events": [
    {
      "type": "sign",
      "x": 23,
      "y": 16,
      "elevation": 0,
      "player_facing_dir": "BG_EVENT_PLAYER_FACING_ANY",
      "script": "PalletTown_Route9Sign"
    }
  ]
}
